rstools/__init__.py
rstools/ensembles.py
rstools/naive_bayes.py
rstools/outliers.py
rstools/statistical_tools.py
rstools/time_series.py
rstools/array_tools/__init__.py
rstools/array_tools/_fix_paths.py
rstools/array_tools/one_d_arrays.py
rstools/forecasting/__init__.py
rstools/forecasting/_fix_paths.py
rstools/forecasting/forecast_mixing.py
rstools/kernels/__init__.py
rstools/kernels/_fix_paths.py
rstools/kernels/discrete_kernels.py
rstools/kernels/kernel_tools.py
rstools/model_fitting/__init__.py
rstools/model_fitting/_fix_paths.py
rstools/model_fitting/mle.py
rstools/optimization/__init__.py
rstools/optimization/_fix_paths.py
rstools/optimization/universal_hyperopt_tuner.py
rstools/probability_distributions/__init__.py
rstools/probability_distributions/_fix_paths.py
rstools/probability_distributions/beta.py
rstools/probability_distributions/binomial_confidence_interval.py
rstools/special_functions/__init__.py
rstools/special_functions/_fix_paths.py
rstools/special_functions/lambert_w.py
rstools/utils/__init__.py
rstools/utils/_fix_paths.py
rstools/utils/pandas_tools.py
rstools-0.0.2.dist-info/METADATA
rstools-0.0.2.dist-info/WHEEL
rstools-0.0.2.dist-info/top_level.txt
rstools-0.0.2.dist-info/RECORD
