Metadata-Version: 2.1
Name: rstools
Version: 0.0.2
Summary: RoomSage library with data science tools
Home-page: UNKNOWN
License: UNKNOWN
Platform: UNKNOWN
Classifier: Programming Language :: Python :: 3.6
Requires-Python: >=3.6
